dec256sinc24b.v
module dec256sinc24b (
    input mclk1,  /* used to clk filter */
    input reset,  /* used to reset filter */
    input mdata1,  /* input data to be filtered
*/
    output reg [15:0] DATA,  /* filtered output
*/
    output reg data_en,
    input [15:0] dec_rate
);
  /* Data is read on positive clk edge */
  reg [36:0] ip_data1;
  reg [36:0] acc1;
  reg [36:0] acc2;
  reg [36:0] acc3;
  reg [36:0] acc3_d2;
  reg [36:0] diff1;
  reg [36:0] diff2;
  reg [36:0] diff3;
  reg [36:0] diff1_d;
  reg [36:0] diff2_d;
  reg [15:0] word_count;
  reg word_clk;
  reg enable;
  /*Perform the Sinc action*/
  always @(mdata1)
    if (mdata1 == 0) ip_data1 <= 37'd0;
    /* change 0 to a -1 for twos
complement */
    else
      ip_data1 <= 37'd1;
  /*Accumulator (Integrator)
Perform the accumulation (IIR) at the speed
of the modulator.
Z = one sample delay MCLKOUT = modulators
conversion bit rate */
  always @(negedge mclk1, posedge reset) begin
    if (reset) begin
      /* initialize acc registers on reset
*/
      acc1 <= 37'd0;
      acc2 <= 37'd0;
      acc3 <= 37'd0;
    end else begin
      /*perform accumulation process */
      acc1 <= acc1 + ip_data1;
      acc2 <= acc2 + acc1;
      acc3 <= acc3 + acc2;
    end
  end

  /*decimation stage (MCLKOUT/WORD_CLK) */
  always @(posedge mclk1, posedge reset) begin
    if (reset) word_count <= 16'd0;
    else begin
      if (word_count == dec_rate - 1) word_count <= 16'd0;
      else word_count <= word_count + 16'b1;
    end
  end
  always @(posedge mclk1, posedge reset) begin
    if (reset) word_clk <= 1'b0;
    else begin
      if (word_count == dec_rate / 2 - 1) word_clk <= 1'b1;
      else if (word_count == dec_rate - 1) word_clk <= 1'b0;
    end
  end

  /*Differentiator (including decimation
stage)
Perform the differentiation stage (FIR) at a
lower speed.
Z = one sample delay WORD_CLK = output word
rate */

  always @(posedge word_clk, posedge reset) begin
    if (reset) begin
      acc3_d2 <= 37'd0;
      diff1_d <= 37'd0;
      diff2_d <= 37'd0;
      diff1   <= 37'd0;
      diff2   <= 37'd0;
      diff3   <= 37'd0;
    end else begin
      diff1   <= acc3 - acc3_d2;
      diff2   <= diff1 - diff1_d;
      diff3   <= diff2 - diff2_d;
      acc3_d2 <= acc3;
      diff1_d <= diff1;
      diff2_d <= diff2;
    end
  end

  /* Clock the Sinc output into an output
register
WORD_CLK = output word rate */

  always @(posedge word_clk) begin
    case (dec_rate)
      16'd32: begin
        DATA <= (diff3[15:0] == 16'h8000) ? 16'hFFFF : {diff3[14:0], 1'b0};
      end
      16'd64: begin
        DATA <= (diff3[18:2] == 17'h10000) ? 16'hFFFF : diff3[17:2];
      end
      16'd128: begin
        DATA <= (diff3[21:5] == 17'h10000) ? 16'hFFFF : diff3[20:5];
      end
      16'd256: begin
        DATA <= (diff3[24:8] == 17'h10000) ? 16'hFFFF : diff3[23:8];
      end
      16'd512: begin
        DATA <= (diff3[27:11] == 17'h10000) ? 16'hFFFF : diff3[26:11];
      end
      16'd1024: begin
        DATA <= (diff3[30:14] == 17'h10000) ? 16'hFFFF : diff3[29:14];
      end
      16'd2048: begin
        DATA <= (diff3[33:17] == 17'h10000) ? 16'hFFFF : diff3[32:17];
      end
      16'd4096: begin
        DATA <= (diff3[36:20] == 17'h10000) ? 16'hFFFF : diff3[35:20];
      end
      default: begin
        DATA <= (diff3[24:8] == 17'h10000) ? 16'hFFFF : diff3[23:8];
      end
    endcase
  end

  /* Synchronize Data Output*/
  always @(posedge mclk1, posedge reset) begin
    if (reset) begin
      data_en <= 1'b0;
      enable  <= 1'b1;
    end else begin
      if ((word_count == dec_rate / 2 - 1) && enable) begin
        data_en <= 1'b1;
        enable  <= 1'b0;
      end else if ((word_count == dec_rate - 1) && ~enable) begin
        data_en <= 1'b0;
        enable  <= 1'b1;
      end else data_en <= 1'b0;
    end
  end
endmodule

dec256sinc24b_waveform.vcd
$version Generated by VerilatedVcd $end
$timescale 1ps $end
 $scope module TOP $end
  $var wire 1 2 mclk1 $end
  $var wire 1 3 reset $end
  $var wire 1 4 mdata1 $end
  $var wire 16 5 DATA [15:0] $end
  $var wire 1 6 data_en $end
  $var wire 16 7 dec_rate [15:0] $end
  $scope module dec256sinc24b $end
   $var wire 1 2 mclk1 $end
   $var wire 1 3 reset $end
   $var wire 1 4 mdata1 $end
   $var wire 16 5 DATA [15:0] $end
   $var wire 1 6 data_en $end
   $var wire 16 7 dec_rate [15:0] $end
   $var wire 37 8 ip_data1 [36:0] $end
   $var wire 37 : acc1 [36:0] $end
   $var wire 37 < acc2 [36:0] $end
   $var wire 37 > acc3 [36:0] $end
   $var wire 37 & acc3_d2 [36:0] $end
   $var wire 37 ( diff1 [36:0] $end
   $var wire 37 * diff2 [36:0] $end
   $var wire 37 , diff3 [36:0] $end
   $var wire 37 . diff1_d [36:0] $end
   $var wire 37 0 diff2_d [36:0] $end
   $var wire 16 # word_count [15:0] $end
   $var wire 1 $ word_clk $end
   $var wire 1 % enable $end
  $upscope $end
 $upscope $end
$enddefinitions $end


#0
b0000000000000000 #
0$
0%
b0000000000000000000000000000000000000 &
b0000000000000000000000000000000000000 (
b0000000000000000000000000000000000000 *
b0000000000000000000000000000000000000 ,
b0000000000000000000000000000000000000 .
b0000000000000000000000000000000000000 0
02
13
04
b0000000000000000 5
06
b0000000100000000 7
b0000000000000000000000000000000000000 8
b0000000000000000000000000000000000000 :
b0000000000000000000000000000000000000 <
b0000000000000000000000000000000000000 >
#5
1%
12
#10
02
#15
12
#20
02
#25
12
#30
02
03
#35
b0000000000000001 #
12
#40
02
#45
b0000000000000010 #
12
#50
02
#55
b0000000000000011 #
12
#60
02
#65
b0000000000000100 #
12
#70
02
#75
b0000000000000101 #
12
#80
02
#85
b0000000000000110 #
12
#90
02
#95
b0000000000000111 #
12
#100
02
#105
b0000000000001000 #
12
#110
02
#115
b0000000000001001 #
12
#120
02
#125
b0000000000001010 #
12
#130
02
#135
b0000000000001011 #
12
#140
02
#145
b0000000000001100 #
12
#150
02
#155
b0000000000001101 #
12
#160
02
#165
b0000000000001110 #
12
#170
02
#175
b0000000000001111 #
12
#180
02
#185
b0000000000010000 #
12
#190
02
#195
b0000000000010001 #
12
#200
02
#205
b0000000000010010 #
12
#210
02
#215
b0000000000010011 #
12
#220
02
#225
b0000000000010100 #
12
#230
02
#235
b0000000000010101 #
12
#240
02
#245
b0000000000010110 #
12
#250
02
#255
b0000000000010111 #
12
#260
02
#265
b0000000000011000 #
12
#270
02
#275
b0000000000011001 #
12
#280
02
#285
b0000000000011010 #
12
#290
02
#295
b0000000000011011 #
12
#300
02
#305
b0000000000011100 #
12
#310
02
#315
b0000000000011101 #
12
#320
02
#325
b0000000000011110 #
12
#330
02
#335
b0000000000011111 #
12
#340
02
#345
b0000000000100000 #
12
#350
02
#355
b0000000000100001 #
12
#360
02
#365
b0000000000100010 #
12
#370
02
#375
b0000000000100011 #
12
#380
02
#385
b0000000000100100 #
12
#390
02
#395
b0000000000100101 #
12
#400
02
#405
b0000000000100110 #
12
#410
02
#415
b0000000000100111 #
12
#420
02
#425
b0000000000101000 #
12
#430
02
#435
b0000000000101001 #
12
#440
02
#445
b0000000000101010 #
12
#450
02
#455
b0000000000101011 #
12
#460
02
#465
b0000000000101100 #
12
#470
02
#475
b0000000000101101 #
12
#480
02
#485
b0000000000101110 #
12
#490
02
#495
b0000000000101111 #
12
#500
02
#505
b0000000000110000 #
12
#510
02
#515
b0000000000110001 #
12
#520
02
#525
b0000000000110010 #
12
#530
02
#535
b0000000000110011 #
12
#540
02
#545
b0000000000110100 #
12
#550
02
#555
b0000000000110101 #
12
#560
02
#565
b0000000000110110 #
12
#570
02
#575
b0000000000110111 #
12
#580
02
#585
b0000000000111000 #
12
#590
02
#595
b0000000000111001 #
12
#600
02
#605
b0000000000111010 #
12
#610
02
#615
b0000000000111011 #
12
#620
02
#625
b0000000000111100 #
12
#630
02
#635
b0000000000111101 #
12
#640
02
#645
b0000000000111110 #
12
#650
02
#655
b0000000000111111 #
12
#660
02
#665
b0000000001000000 #
12
#670
02
#675
b0000000001000001 #
12
#680
02
#685
b0000000001000010 #
12
#690
02
#695
b0000000001000011 #
12
#700
02
#705
b0000000001000100 #
12
#710
02
#715
b0000000001000101 #
12
#720
02
#725
b0000000001000110 #
12
#730
02
#735
b0000000001000111 #
12
#740
02
#745
b0000000001001000 #
12
#750
02
#755
b0000000001001001 #
12
#760
02
#765
b0000000001001010 #
12
#770
02
#775
b0000000001001011 #
12
#780
02
#785
b0000000001001100 #
12
#790
02
#795
b0000000001001101 #
12
#800
02
#805
b0000000001001110 #
12
#810
02
#815
b0000000001001111 #
12
#820
02
#825
b0000000001010000 #
12
#830
02
#835
b0000000001010001 #
12
#840
02
#845
b0000000001010010 #
12
#850
02
#855
b0000000001010011 #
12
#860
02
#865
b0000000001010100 #
12
#870
02
#875
b0000000001010101 #
12
#880
02
#885
b0000000001010110 #
12
#890
02
#895
b0000000001010111 #
12
#900
02
#905
b0000000001011000 #
12
#910
02
#915
b0000000001011001 #
12
#920
02
#925
b0000000001011010 #
12
#930
02
#935
b0000000001011011 #
12
#940
02
#945
b0000000001011100 #
12
#950
02
#955
b0000000001011101 #
12
#960
02
#965
b0000000001011110 #
12
#970
02
#975
b0000000001011111 #
12
#980
02
#985
b0000000001100000 #
12
#990
02
#995
b0000000001100001 #
12
#1000
02
#1005
b0000000001100010 #
12
#1010
02
#1015
b0000000001100011 #
12
#1020
02
#1025
b0000000001100100 #
12
#1030
02
#1035
b0000000001100101 #
12
#1040
02
#1045
b0000000001100110 #
12
#1050
02
#1055
b0000000001100111 #
12
#1060
02
#1065
b0000000001101000 #
12
#1070
02
#1075
b0000000001101001 #
12
#1080
02
#1085
b0000000001101010 #
12
#1090
02
#1095
b0000000001101011 #
12
#1100
02
#1105
b0000000001101100 #
12
#1110
02
#1115
b0000000001101101 #
12
#1120
02
#1125
b0000000001101110 #
12
#1130
02
#1135
b0000000001101111 #
12
#1140
02
#1145
b0000000001110000 #
12
#1150
02
#1155
b0000000001110001 #
12
#1160
02
#1165
b0000000001110010 #
12
#1170
02
#1175
b0000000001110011 #
12
#1180
02
#1185
b0000000001110100 #
12
#1190
02
#1195
b0000000001110101 #
12
#1200
02
#1205
b0000000001110110 #
12
#1210
02
#1215
b0000000001110111 #
12
#1220
02
#1225
b0000000001111000 #
12
#1230
02
#1235
b0000000001111001 #
12
#1240
02
#1245
b0000000001111010 #
12
#1250
02
#1255
b0000000001111011 #
12
#1260
02
#1265
b0000000001111100 #
12
#1270
02
#1275
b0000000001111101 #
12
#1280
02
#1285
b0000000001111110 #
12
#1290
02
#1295
b0000000001111111 #
12
#1300
02
#1305
b0000000010000000 #
1$
0%
12
16
#1310
02
#1315
b0000000010000001 #
12
06
#1320
02
#1325
b0000000010000010 #
12
#1330
02
#1335
b0000000010000011 #
12
#1340
02
#1345
b0000000010000100 #
12
#1350
02
#1355
b0000000010000101 #
12
#1360
02
#1365
b0000000010000110 #
12
#1370
02
#1375
b0000000010000111 #
12
#1380
02
#1385
b0000000010001000 #
12
#1390
02
#1395
b0000000010001001 #
12
#1400
02
#1405
b0000000010001010 #
12
#1410
02
#1415
b0000000010001011 #
12
#1420
02
#1425
b0000000010001100 #
12
#1430
02
#1435
b0000000010001101 #
12
#1440
02
#1445
b0000000010001110 #
12
#1450
02
#1455
b0000000010001111 #
12
#1460
02
#1465
b0000000010010000 #
12
#1470
02
#1475
b0000000010010001 #
12
#1480
02
#1485
b0000000010010010 #
12
#1490
02
#1495
b0000000010010011 #
12
#1500
02
#1505
b0000000010010100 #
12
#1510
02
#1515
b0000000010010101 #
12
#1520
02
#1525
b0000000010010110 #
12
#1530
02
#1535
b0000000010010111 #
12
#1540
02
#1545
b0000000010011000 #
12
#1550
02
#1555
b0000000010011001 #
12
#1560
02
#1565
b0000000010011010 #
12
#1570
02
#1575
b0000000010011011 #
12
#1580
02
#1585
b0000000010011100 #
12
#1590
02
#1595
b0000000010011101 #
12
#1600
02
#1605
b0000000010011110 #
12
#1610
02
#1615
b0000000010011111 #
12
#1620
02
#1625
b0000000010100000 #
12
#1630
02
#1635
b0000000010100001 #
12
#1640
02
#1645
b0000000010100010 #
12
#1650
02
#1655
b0000000010100011 #
12
#1660
02
#1665
b0000000010100100 #
12
#1670
02
#1675
b0000000010100101 #
12
#1680
02
#1685
b0000000010100110 #
12
#1690
02
#1695
b0000000010100111 #
12
#1700
02
#1705
b0000000010101000 #
12
#1710
02
#1715
b0000000010101001 #
12
#1720
02
#1725
b0000000010101010 #
12
#1730
02
#1735
b0000000010101011 #
12
#1740
02
#1745
b0000000010101100 #
12
#1750
02
#1755
b0000000010101101 #
12
#1760
02
#1765
b0000000010101110 #
12
#1770
02
#1775
b0000000010101111 #
12
#1780
02
#1785
b0000000010110000 #
12
#1790
02
#1795
b0000000010110001 #
12
#1800
02
#1805
b0000000010110010 #
12
#1810
02
#1815
b0000000010110011 #
12
#1820
02
#1825
b0000000010110100 #
12
#1830
02
#1835
b0000000010110101 #
12
#1840
02
#1845
b0000000010110110 #
12
#1850
02
#1855
b0000000010110111 #
12
#1860
02
#1865
b0000000010111000 #
12
#1870
02
#1875
b0000000010111001 #
12
#1880
02
#1885
b0000000010111010 #
12
#1890
02
#1895
b0000000010111011 #
12
#1900
02
#1905
b0000000010111100 #
12
#1910
02
#1915
b0000000010111101 #
12
#1920
02
#1925
b0000000010111110 #
12
#1930
02
#1935
b0000000010111111 #
12
#1940
02
#1945
b0000000011000000 #
12
#1950
02
#1955
b0000000011000001 #
12
#1960
02
#1965
b0000000011000010 #
12
#1970
02
#1975
b0000000011000011 #
12
#1980
02
#1985
b0000000011000100 #
12
#1990
02
#1995
b0000000011000101 #
12
#2000
02
#2005
b0000000011000110 #
12
#2010
02
#2015
b0000000011000111 #
12
#2020
02
#2025
b0000000011001000 #
12
#2030
02
#2035
b0000000011001001 #
12
#2040
02
#2045
b0000000011001010 #
12
#2050
02
#2055
b0000000011001011 #
12
#2060
02
#2065
b0000000011001100 #
12
#2070
02
#2075
b0000000011001101 #
12
#2080
02
#2085
b0000000011001110 #
12
#2090
02
#2095
b0000000011001111 #
12
#2100
02
#2105
b0000000011010000 #
12
#2110
02
#2115
b0000000011010001 #
12
#2120
02
#2125
b0000000011010010 #
12
#2130
02
#2135
b0000000011010011 #
12
#2140
02
#2145
b0000000011010100 #
12
#2150
02
#2155
b0000000011010101 #
12
#2160
02
#2165
b0000000011010110 #
12
#2170
02
#2175
b0000000011010111 #
12
#2180
02
#2185
b0000000011011000 #
12
#2190
02
#2195
b0000000011011001 #
12
#2200
02
#2205
b0000000011011010 #
12
#2210
02
#2215
b0000000011011011 #
12
#2220
02
#2225
b0000000011011100 #
12
#2230
02
#2235
b0000000011011101 #
12
#2240
02
#2245
b0000000011011110 #
12
#2250
02
#2255
b0000000011011111 #
12
#2260
02
#2265
b0000000011100000 #
12
#2270
02
#2275
b0000000011100001 #
12
#2280
02
#2285
b0000000011100010 #
12
#2290
02
#2295
b0000000011100011 #
12
#2300
02
#2305
b0000000011100100 #
12
#2310
02
#2315
b0000000011100101 #
12
#2320
02
#2325
b0000000011100110 #
12
#2330
02
#2335
b0000000011100111 #
12
#2340
02
#2345
b0000000011101000 #
12
#2350
02
#2355
b0000000011101001 #
12
#2360
02
#2365
b0000000011101010 #
12
#2370
02
#2375
b0000000011101011 #
12
#2380
02
#2385
b0000000011101100 #
12
#2390
02
#2395
b0000000011101101 #
12
#2400
02
#2405
b0000000011101110 #
12
#2410
02
#2415
b0000000011101111 #
12
#2420
02
#2425
b0000000011110000 #
12
#2430
02
#2435
b0000000011110001 #
12
#2440
02
#2445
b0000000011110010 #
12
#2450
02
#2455
b0000000011110011 #
12
#2460
02
#2465
b0000000011110100 #
12
#2470
02
#2475
b0000000011110101 #
12
#2480
02
#2485
b0000000011110110 #
12
#2490
02
#2495
b0000000011110111 #
12
#2500
02
#2505
b0000000011111000 #
12
#2510
02
#2515
b0000000011111001 #
12
#2520
02
#2525
b0000000011111010 #
12
#2530
02
#2535
b0000000011111011 #
12
#2540
02
#2545
b0000000011111100 #
12
#2550
02
#2555
b0000000011111101 #
12
#2560
02
#2565
b0000000011111110 #
12
#2570
02
#2575
b0000000011111111 #
12
#2580
02
#2585
b0000000000000000 #
0$
1%
12
#2590
02
#2595
b0000000000000001 #
12
#2600
02
#2605
b0000000000000010 #
12
#2610
02
#2615
b0000000000000011 #
12
#2620
02
#2625
b0000000000000100 #
12
#2630
02
#2635
b0000000000000101 #
12
#2640
02
#2645
b0000000000000110 #
12
#2650
02
#2655
b0000000000000111 #
12
#2660
02
#2665
b0000000000001000 #
12
#2670
02
#2675
b0000000000001001 #
12
#2680
02
#2685
b0000000000001010 #
12
#2690
02
#2695
b0000000000001011 #
12
#2700
02
#2705
b0000000000001100 #
12
#2710
02
#2715
b0000000000001101 #
12
#2720
02
#2725
b0000000000001110 #
12
#2730
02
#2735
b0000000000001111 #
12
#2740
02
#2745
b0000000000010000 #
12
#2750
02
#2755
b0000000000010001 #
12
#2760
02
#2765
b0000000000010010 #
12
#2770
02
#2775
b0000000000010011 #
12
#2780
02
#2785
b0000000000010100 #
12
#2790
02
#2795
b0000000000010101 #
12
#2800
02
#2805
b0000000000010110 #
12
#2810
02
#2815
b0000000000010111 #
12
#2820
02
#2825
b0000000000011000 #
12
#2830
02
#2835
b0000000000011001 #
12
#2840
02
#2845
b0000000000011010 #
12
#2850
02
#2855
b0000000000011011 #
12
#2860
02
#2865
b0000000000011100 #
12
#2870
02
#2875
b0000000000011101 #
12
#2880
02
#2885
b0000000000011110 #
12
#2890
02
#2895
b0000000000011111 #
12
#2900
02
#2905
b0000000000100000 #
12
#2910
02
#2915
b0000000000100001 #
12
#2920
02
#2925
b0000000000100010 #
12
#2930
02
#2935
b0000000000100011 #
12
#2940
02
#2945
b0000000000100100 #
12
#2950
02
#2955
b0000000000100101 #
12
#2960
02
#2965
b0000000000100110 #
12
#2970
02
#2975
b0000000000100111 #
12
#2980
02
#2985
b0000000000101000 #
12
#2990
02
#2995
b0000000000101001 #
12
#3000
02
#3005
b0000000000101010 #
12
#3010
02
#3015
b0000000000101011 #
12
#3020
02
#3025
b0000000000101100 #
12
#3030
02
#3035
b0000000000101101 #
12
#3040
02
#3045
b0000000000101110 #
12
#3050
02
#3055
b0000000000101111 #
12
#3060
02
#3065
b0000000000110000 #
12
#3070
02
#3075
b0000000000110001 #
12
#3080
02
#3085
b0000000000110010 #
12
#3090
02
#3095
b0000000000110011 #
12
#3100
02
#3105
b0000000000110100 #
12
#3110
02
#3115
b0000000000110101 #
12
#3120
02
#3125
b0000000000110110 #
12
#3130
02
#3135
b0000000000110111 #
12
#3140
02
#3145
b0000000000111000 #
12
#3150
02
#3155
b0000000000111001 #
12
#3160
02
#3165
b0000000000111010 #
12
#3170
02
#3175
b0000000000111011 #
12
#3180
02
#3185
b0000000000111100 #
12
#3190
02
#3195
b0000000000111101 #
12
#3200
02
#3205
b0000000000111110 #
12
#3210
02
#3215
b0000000000111111 #
12
#3220
02
#3225
b0000000001000000 #
12
#3230
02
#3235
b0000000001000001 #
12
#3240
02
#3245
b0000000001000010 #
12
#3250
02
#3255
b0000000001000011 #
12
#3260
02
#3265
b0000000001000100 #
12
#3270
02
#3275
b0000000001000101 #
12
#3280
02
#3285
b0000000001000110 #
12
#3290
02
#3295
b0000000001000111 #
12
#3300
02
#3305
b0000000001001000 #
12
#3310
02
#3315
b0000000001001001 #
12
#3320
02
#3325
b0000000001001010 #
12
#3330
02
#3335
b0000000001001011 #
12
#3340
02
#3345
b0000000001001100 #
12
#3350
02
#3355
b0000000001001101 #
12
#3360
02
#3365
b0000000001001110 #
12
#3370
02
#3375
b0000000001001111 #
12
#3380
02
#3385
b0000000001010000 #
12
#3390
02
#3395
b0000000001010001 #
12
#3400
02
#3405
b0000000001010010 #
12
#3410
02
#3415
b0000000001010011 #
12
#3420
02
#3425
b0000000001010100 #
12
#3430
02
#3435
b0000000001010101 #
12
#3440
02
#3445
b0000000001010110 #
12
#3450
02
#3455
b0000000001010111 #
12
#3460
02
#3465
b0000000001011000 #
12
#3470
02
#3475
b0000000001011001 #
12
#3480
02
#3485
b0000000001011010 #
12
#3490
02
#3495
b0000000001011011 #
12
#3500
02
#3505
b0000000001011100 #
12
#3510
02
#3515
b0000000001011101 #
12
#3520
02
#3525
b0000000001011110 #
12
#3530
02
#3535
b0000000001011111 #
12
#3540
02
#3545
b0000000001100000 #
12
#3550
02
#3555
b0000000001100001 #
12
#3560
02
#3565
b0000000001100010 #
12
#3570
02
#3575
b0000000001100011 #
12
#3580
02
#3585
b0000000001100100 #
12
#3590
02
#3595
b0000000001100101 #
12
#3600
02
#3605
b0000000001100110 #
12
#3610
02
#3615
b0000000001100111 #
12
#3620
02
#3625
b0000000001101000 #
12
#3630
02
#3635
b0000000001101001 #
12
#3640
02
#3645
b0000000001101010 #
12
#3650
02
#3655
b0000000001101011 #
12
#3660
02
#3665
b0000000001101100 #
12
#3670
02
#3675
b0000000001101101 #
12
#3680
02
#3685
b0000000001101110 #
12
#3690
02
#3695
b0000000001101111 #
12
#3700
02
#3705
b0000000001110000 #
12
#3710
02
#3715
b0000000001110001 #
12
#3720
02
#3725
b0000000001110010 #
12
#3730
02
#3735
b0000000001110011 #
12
#3740
02
#3745
b0000000001110100 #
12
#3750
02
#3755
b0000000001110101 #
12
#3760
02
#3765
b0000000001110110 #
12
#3770
02
#3775
b0000000001110111 #
12
#3780
02
#3785
b0000000001111000 #
12
#3790
02
#3795
b0000000001111001 #
12
#3800
02
#3805
b0000000001111010 #
12
#3810
02
#3815
b0000000001111011 #
12
#3820
02
#3825
b0000000001111100 #
12
#3830
02
#3835
b0000000001111101 #
12
#3840
02
#3845
b0000000001111110 #
12
#3850
02
#3855
b0000000001111111 #
12
#3860
02
#3865
b0000000010000000 #
1$
0%
12
16
#3870
02
#3875
b0000000010000001 #
12
06
#3880
02
#3885
b0000000010000010 #
12
#3890
02
#3895
b0000000010000011 #
12
#3900
02
#3905
b0000000010000100 #
12
#3910
02
#3915
b0000000010000101 #
12
#3920
02
#3925
b0000000010000110 #
12
#3930
02
#3935
b0000000010000111 #
12
#3940
02
#3945
b0000000010001000 #
12
#3950
02
#3955
b0000000010001001 #
12
#3960
02
#3965
b0000000010001010 #
12
#3970
02
#3975
b0000000010001011 #
12
#3980
02
#3985
b0000000010001100 #
12
#3990
02
#3995
b0000000010001101 #
12
#4000
02
#4005
b0000000010001110 #
12
#4010
02
#4015
b0000000010001111 #
12
#4020
02
#4025
b0000000010010000 #
12
#4030
02
#4035
b0000000010010001 #
12
#4040
02
#4045
b0000000010010010 #
12
#4050
02
#4055
b0000000010010011 #
12
#4060
02
#4065
b0000000010010100 #
12
#4070
02
#4075
b0000000010010101 #
12
#4080
02
#4085
b0000000010010110 #
12
#4090
02
#4095
b0000000010010111 #
12
#4100
02
#4105
b0000000010011000 #
12
#4110
02
#4115
b0000000010011001 #
12
#4120
02
#4125
b0000000010011010 #
12
#4130
02
#4135
b0000000010011011 #
12
#4140
02
#4145
b0000000010011100 #
12
#4150
02
#4155
b0000000010011101 #
12
#4160
02
#4165
b0000000010011110 #
12
#4170
02
#4175
b0000000010011111 #
12
#4180
02
#4185
b0000000010100000 #
12
#4190
02
#4195
b0000000010100001 #
12
#4200
02
#4205
b0000000010100010 #
12
#4210
02
#4215
b0000000010100011 #
12
#4220
02
#4225
b0000000010100100 #
12
#4230
02
#4235
b0000000010100101 #
12
#4240
02
#4245
b0000000010100110 #
12
#4250
02
#4255
b0000000010100111 #
12
#4260
02
#4265
b0000000010101000 #
12
#4270
02
#4275
b0000000010101001 #
12
#4280
02
#4285
b0000000010101010 #
12
#4290
02
#4295
b0000000010101011 #
12
#4300
02
#4305
b0000000010101100 #
12
#4310
02
#4315
b0000000010101101 #
12
#4320
02
#4325
b0000000010101110 #
12
#4330
02
#4335
b0000000010101111 #
12
#4340
02
#4345
b0000000010110000 #
12
#4350
02
#4355
b0000000010110001 #
12
#4360
02
#4365
b0000000010110010 #
12
#4370
02
#4375
b0000000010110011 #
12
#4380
02
#4385
b0000000010110100 #
12
#4390
02
#4395
b0000000010110101 #
12
#4400
02
#4405
b0000000010110110 #
12
#4410
02
#4415
b0000000010110111 #
12
#4420
02
#4425
b0000000010111000 #
12
#4430
02
#4435
b0000000010111001 #
12
#4440
02
#4445
b0000000010111010 #
12
#4450
02
#4455
b0000000010111011 #
12
#4460
02
#4465
b0000000010111100 #
12
#4470
02
#4475
b0000000010111101 #
12
#4480
02
#4485
b0000000010111110 #
12
#4490
02
#4495
b0000000010111111 #
12
#4500
02
#4505
b0000000011000000 #
12
#4510
02
#4515
b0000000011000001 #
12
#4520
02
#4525
b0000000011000010 #
12
#4530
02
#4535
b0000000011000011 #
12
#4540
02
#4545
b0000000011000100 #
12
#4550
02
#4555
b0000000011000101 #
12
#4560
02
#4565
b0000000011000110 #
12
#4570
02
#4575
b0000000011000111 #
12
#4580
02
#4585
b0000000011001000 #
12
#4590
02
#4595
b0000000011001001 #
12
#4600
02
#4605
b0000000011001010 #
12
#4610
02
#4615
b0000000011001011 #
12
#4620
02
#4625
b0000000011001100 #
12
#4630
02
#4635
b0000000011001101 #
12
#4640
02
#4645
b0000000011001110 #
12
#4650
02
#4655
b0000000011001111 #
12
#4660
02
#4665
b0000000011010000 #
12
#4670
02
#4675
b0000000011010001 #
12
#4680
02
#4685
b0000000011010010 #
12
#4690
02
#4695
b0000000011010011 #
12
#4700
02
#4705
b0000000011010100 #
12
#4710
02
#4715
b0000000011010101 #
12
#4720
02
#4725
b0000000011010110 #
12
#4730
02
#4735
b0000000011010111 #
12
#4740
02
#4745
b0000000011011000 #
12
#4750
02
#4755
b0000000011011001 #
12
#4760
02
#4765
b0000000011011010 #
12
#4770
02
#4775
b0000000011011011 #
12
#4780
02
#4785
b0000000011011100 #
12
#4790
02
#4795
b0000000011011101 #
12
#4800
02
#4805
b0000000011011110 #
12
#4810
02
#4815
b0000000011011111 #
12
#4820
02
#4825
b0000000011100000 #
12
#4830
02
#4835
b0000000011100001 #
12
#4840
02
#4845
b0000000011100010 #
12
#4850
02
#4855
b0000000011100011 #
12
#4860
02
#4865
b0000000011100100 #
12
#4870
02
#4875
b0000000011100101 #
12
#4880
02
#4885
b0000000011100110 #
12
#4890
02
#4895
b0000000011100111 #
12
#4900
02
#4905
b0000000011101000 #
12
#4910
02
#4915
b0000000011101001 #
12
#4920
02
#4925
b0000000011101010 #
12
#4930
02
#4935
b0000000011101011 #
12
#4940
02
#4945
b0000000011101100 #
12
#4950
02
#4955
b0000000011101101 #
12
#4960
02
#4965
b0000000011101110 #
12
#4970
02
#4975
b0000000011101111 #
12
#4980
02
#4985
b0000000011110000 #
12
#4990
02
#4995
b0000000011110001 #
12
#5000
02
#5005
b0000000011110010 #
12
#5010
02
#5015
b0000000011110011 #
12
#5020
02
#5025
b0000000011110100 #
12
#5030
02
#5035
b0000000011110101 #
12
#5040
02
#5045
b0000000011110110 #
12
#5050
02
#5055
b0000000011110111 #
12
#5060
02
#5065
b0000000011111000 #
12
#5070
02
#5075
b0000000011111001 #
12
#5080
02
#5085
b0000000011111010 #
12
#5090
02
#5095
b0000000011111011 #
12
#5100
02
#5105
b0000000011111100 #
12
#5110
02
#5115
b0000000011111101 #
12
#5120
02
#5125
b0000000011111110 #
12
#5130
02
#5135
b0000000011111111 #
12
#5140
02
#5145
b0000000000000000 #
0$
1%
12
#5150
02
#5155
b0000000000000001 #
12
#5160
02
#5165
b0000000000000010 #
12
#5170
02
#5175
b0000000000000011 #
12
#5180
02
#5185
b0000000000000100 #
12
#5190
02
#5195
b0000000000000101 #
12
#5200
02
#5205
b0000000000000110 #
12
#5210
02
#5215
b0000000000000111 #
12
#5220
02
#5225
b0000000000001000 #
12
#5230
02
#5235
b0000000000001001 #
12
#5240
02
#5245
b0000000000001010 #
12
#5250
02
#5255
b0000000000001011 #
12
#5260
02
#5265
b0000000000001100 #
12
#5270
02
#5275
b0000000000001101 #
12
#5280
02
#5285
b0000000000001110 #
12
#5290
02
#5295
b0000000000001111 #
12
#5300
02
#5305
b0000000000010000 #
12
#5310
02
#5315
b0000000000010001 #
12
#5320
02
#5325
b0000000000010010 #
12
#5330
02
#5335
b0000000000010011 #
12
#5340
02
#5345
b0000000000010100 #
12
#5350
02
#5355
b0000000000010101 #
12
#5360
02
#5365
b0000000000010110 #
12
#5370
02
#5375
b0000000000010111 #
12
#5380
02
#5385
b0000000000011000 #
12
#5390
02
#5395
b0000000000011001 #
12
#5400
02
#5405
b0000000000011010 #
12
#5410
02
#5415
b0000000000011011 #
12
#5420
02
#5425
b0000000000011100 #
12
#5430
02
#5435
b0000000000011101 #
12
#5440
02
#5445
b0000000000011110 #
12
#5450
02
#5455
b0000000000011111 #
12
#5460
02
#5465
b0000000000100000 #
12
#5470
02
#5475
b0000000000100001 #
12
#5480
02
#5485
b0000000000100010 #
12
#5490
02
#5495
b0000000000100011 #
12
#5500
02
#5505
b0000000000100100 #
12
#5510
02
#5515
b0000000000100101 #
12
#5520
02
#5525
b0000000000100110 #
12
#5530
02
#5535
b0000000000100111 #
12
#5540
02
#5545
b0000000000101000 #
12
#5550
02
#5555
b0000000000101001 #
12
#5560
02
#5565
b0000000000101010 #
12
#5570
02
#5575
b0000000000101011 #
12
#5580
02
#5585
b0000000000101100 #
12
#5590
02
#5595
b0000000000101101 #
12
#5600
02
#5605
b0000000000101110 #
12
#5610
02
#5615
b0000000000101111 #
12
#5620
02
#5625
b0000000000110000 #
12
#5630
02
#5635
b0000000000110001 #
12
#5640
02
#5645
b0000000000110010 #
12
#5650
02
